hyperspy_gui_traitsui/__init__.py
hyperspy_gui_traitsui/axes.py
hyperspy_gui_traitsui/buttons.py
hyperspy_gui_traitsui/hyperspy_extension.yaml
hyperspy_gui_traitsui/messages.py
hyperspy_gui_traitsui/microscope_parameters.py
hyperspy_gui_traitsui/model.py
hyperspy_gui_traitsui/preferences.py
hyperspy_gui_traitsui/roi.py
hyperspy_gui_traitsui/tools.py
hyperspy_gui_traitsui/utils.py
hyperspy_gui_traitsui/_external/bounds_editor.py
hyperspy_gui_traitsui/_external/range_slider.py
hyperspy_gui_traitsui/tests/__init__.py
hyperspy_gui_traitsui/tests/test_axes.py
hyperspy_gui_traitsui/tests/test_import.py
hyperspy_gui_traitsui/tests/test_model.py
hyperspy_gui_traitsui/tests/test_tools.py
hyperspy_gui_traitsui/tests/utils.py
hyperspy_gui_traitsui-2.1.1.dist-info/licenses/LICENSE
hyperspy_gui_traitsui-2.1.1.dist-info/METADATA
hyperspy_gui_traitsui-2.1.1.dist-info/WHEEL
hyperspy_gui_traitsui-2.1.1.dist-info/entry_points.txt
hyperspy_gui_traitsui-2.1.1.dist-info/top_level.txt
hyperspy_gui_traitsui-2.1.1.dist-info/RECORD
