Metadata-Version: 2.4
Name: hyperspy_gui_traitsui
Version: 2.1.1
Summary: traitsui GUI elements for the HyperSpy framework.
License:                     GNU GENERAL PUBLIC LICENSE
Project-URL: Homepage, https://github.com/hyperspy/hyperspy_gui_traitsui
Project-URL: Bug Reports, https://github.com/hyperspy/hyperspy_gui_traitsui/issues
Project-URL: Source, https://github.com/hyperspy/hyperspy_gui_traitsui
Project-URL: Conda-Forge, https://anaconda.org/conda-forge/hyperspy-gui-traitsui
Project-URL: Support, https://gitter.im/hyperspy/hyperspy
Keywords: data analysis,microscopy,traitsui,hyperspy,multi-dimensional
Classifier: Development Status :: 4 - Beta
Classifier: Intended Audience :: Developers
Classifier: Intended Audience :: Science/Research
Classifier: Topic :: Software Development :: Libraries
Classifier: Topic :: Scientific/Engineering
Classifier: License :: OSI Approved :: GNU General Public License v3 (GPLv3)
Classifier: Programming Language :: Python :: 3.9
Classifier: Programming Language :: Python :: 3.10
Classifier: Programming Language :: Python :: 3.11
Classifier: Programming Language :: Python :: 3.12
Classifier: Programming Language :: Python :: 3.13
Classifier: Operating System :: Microsoft :: Windows
Classifier: Operating System :: POSIX
Classifier: Operating System :: Unix
Classifier: Operating System :: MacOS
Requires-Python: >=3.9
License-File: LICENSE
Requires-Dist: hyperspy>=2.3.0
Requires-Dist: traits>=6.3
Requires-Dist: traitsui>=7.3
Provides-Extra: tests
Requires-Dist: pytest; extra == "tests"
Requires-Dist: pytest-cov; extra == "tests"
Requires-Dist: pytest-rerunfailures; extra == "tests"
Requires-Dist: setuptools-scm; extra == "tests"
Provides-Extra: dev
Requires-Dist: black; extra == "dev"
Requires-Dist: hyperspy-gui-traitsui[doc]; extra == "dev"
Requires-Dist: hyperspy-gui-traitsui[tests]; extra == "dev"
Dynamic: license-file
